unimorph.py
unimorph-0.0.4.dist-info/METADATA
unimorph-0.0.4.dist-info/WHEEL
unimorph-0.0.4.dist-info/entry_points.txt
unimorph-0.0.4.dist-info/top_level.txt
unimorph-0.0.4.dist-info/RECORD
