Metadata-Version: 2.1
Name: unimorph
Version: 0.0.4
Summary: Annotated morphology in the world's languages
Home-page: https://unimorph.github.io/
Author: Arya D. McCarthy
Author-email: arya@jhu.edu
Maintainer-email: arya@jhu.edu
License: UNKNOWN
Keywords: NLP,natural language processing,evaluation,computational linguistics,morphology
Platform: UNKNOWN
Classifier: Development Status :: 4 - Beta
Classifier: Intended Audience :: Developers
Classifier: Intended Audience :: Science/Research
Classifier: Topic :: Scientific/Engineering
Classifier: Topic :: Scientific/Engineering :: Artificial Intelligence
Classifier: Topic :: Text Processing
Classifier: Programming Language :: Python :: 3 :: Only
Requires-Python: >=3.6
Requires-Dist: pandas
